Client/Client_database_creation.py
Client/Metaclasses.py
Client/__init__.py
Client/client.py
Client/client_window.py
Client/client_window_2.py
Client/client_window_3.py
Client/descriptor.py
Client/launcher.py
client_chat_tcp_ip-0.8.7.dist-info/METADATA
client_chat_tcp_ip-0.8.7.dist-info/WHEEL
client_chat_tcp_ip-0.8.7.dist-info/top_level.txt
client_chat_tcp_ip-0.8.7.dist-info/RECORD
