Metadata-Version: 2.1
Name: client-chat-tcp-ip
Version: 0.8.7
Summary: client
Home-page: https://github.com/rlrl23/Async_chat
Author: Liubov Ilinykh
Author-email: lrlr2393@gmail.com
Requires-Dist: PyQt5
Requires-Dist: sqlalchemy
Requires-Dist: pycryptodome
Requires-Dist: pycryptodomex
